{"nodes": [{"id": "agents_md", "label": "Semillas Agent Instructions (OpenCode)", "file_type": "document", "source_file": "AGENTS.md", "source_location": null, "source_url": null, "captured_at": null, "author": null, "contributor": null}, {"id": "concept_offline_first_architecture", "label": "Offline-First Architecture", "file_type": "rationale", "source_file": "AGENTS.md", "source_location": null, "source_url": null, "captured_at": null, "author": null, "contributor": null}, {"id": "concept_idempotent_sync", "label": "Idempotent Sync Pattern", "file_type": "rationale", "source_file": "AGENTS.md", "source_location": null, "source_url": null, "captured_at": null, "author": null, "contributor": null}, {"id": "concept_cms_publication_workflow", "label": "CMS Publication Workflow", "file_type": "rationale", "source_file": "AGENTS.md", "source_location": null, "source_url": null, "captured_at": null, "author": null, "contributor": null}, {"id": "concept_minor_protection_security", "label": "Minor Protection Security Model", "file_type": "rationale", "source_file": "AGENTS.md", "source_location": null, "source_url": null, "captured_at": null, "author": null, "contributor": null}, {"id": "concept_pwa_instalable", "label": "Installable PWA", "file_type": "concept", "source_file": "AGENTS.md", "source_location": null, "source_url": null, "captured_at": null, "author": null, "contributor": null}, {"id": "concept_single_pwa_response", "label": "Single Responsive PWA Decision", "file_type": "rationale", "source_file": "AGENTS.md", "source_location": null, "source_url": null, "captured_at": null, "author": null, "contributor": null}, {"id": "concept_ai_assisted_cms", "label": "AI-Assisted CMS (No Auto-Publish)", "file_type": "rationale", "source_file": "AGENTS.md", "source_location": null, "source_url": null, "captured_at": null, "author": null, "contributor": null}, {"id": "concept_content_state_machine", "label": "Content State Machine (Draft/Review/Published/Archived)", "file_type": "rationale", "source_file": "AGENTS.md", "source_location": null, "source_url": null, "captured_at": null, "author": null, "contributor": null}, {"id": "concept_dexie_outbox", "label": "Dexie Outbox Pattern for Offline Sync", "file_type": "rationale", "source_file": "AGENTS.md", "source_location": null, "source_url": null, "captured_at": null, "author": null, "contributor": null}, {"id": "concept_zod_validation", "label": "Zod Validation Everywhere", "file_type": "rationale", "source_file": "AGENTS.md", "source_location": null, "source_url": null, "captured_at": null, "author": null, "contributor": null}, {"id": "concept_supabase_rls_second_layer", "label": "Supabase RLS as Second Security Layer", "file_type": "rationale", "source_file": "AGENTS.md", "source_location": null, "source_url": null, "captured_at": null, "author": null, "contributor": null}], "edges": [{"source": "agents_md", "target": "concept_semillas_platform", "relation": "references", "confidence": "EXTRACTED", "confidence_score": 1.0, "source_file": "AGENTS.md", "source_location": null, "weight": 1.0}, {"source": "agents_md", "target": "concept_crecer_methodology", "relation": "references", "confidence": "EXTRACTED", "confidence_score": 1.0, "source_file": "AGENTS.md", "source_location": null, "weight": 1.0}, {"source": "agents_md", "target": "concept_offline_first_architecture", "relation": "references", "confidence": "EXTRACTED", "confidence_score": 1.0, "source_file": "AGENTS.md", "source_location": null, "weight": 1.0}, {"source": "agents_md", "target": "concept_cloudflare_workers_api", "relation": "references", "confidence": "EXTRACTED", "confidence_score": 1.0, "source_file": "AGENTS.md", "source_location": null, "weight": 1.0}, {"source": "agents_md", "target": "concept_cms_publication_workflow", "relation": "references", "confidence": "EXTRACTED", "confidence_score": 1.0, "source_file": "AGENTS.md", "source_location": null, "weight": 1.0}, {"source": "agents_md", "target": "concept_minor_protection_security", "relation": "references", "confidence": "EXTRACTED", "confidence_score": 1.0, "source_file": "AGENTS.md", "source_location": null, "weight": 1.0}, {"source": "agents_md", "target": "concept_ai_assisted_cms", "relation": "references", "confidence": "EXTRACTED", "confidence_score": 1.0, "source_file": "AGENTS.md", "source_location": null, "weight": 1.0}, {"source": "agents_md", "target": "concept_single_pwa_response", "relation": "references", "confidence": "EXTRACTED", "confidence_score": 1.0, "source_file": "AGENTS.md", "source_location": null, "weight": 1.0}, {"source": "agents_md", "target": "concept_dexie_outbox", "relation": "references", "confidence": "EXTRACTED", "confidence_score": 1.0, "source_file": "AGENTS.md", "source_location": null, "weight": 1.0}, {"source": "agents_md", "target": "concept_content_state_machine", "relation": "references", "confidence": "EXTRACTED", "confidence_score": 1.0, "source_file": "AGENTS.md", "source_location": null, "weight": 1.0}, {"source": "agents_md", "target": "concept_zod_validation", "relation": "references", "confidence": "EXTRACTED", "confidence_score": 1.0, "source_file": "AGENTS.md", "source_location": null, "weight": 1.0}, {"source": "agents_md", "target": "concept_supabase_rls_second_layer", "relation": "references", "confidence": "EXTRACTED", "confidence_score": 1.0, "source_file": "AGENTS.md", "source_location": null, "weight": 1.0}, {"source": "concept_offline_first_architecture", "target": "concept_dexie_outbox", "relation": "conceptually_related_to", "confidence": "EXTRACTED", "confidence_score": 1.0, "source_file": "AGENTS.md", "source_location": null, "weight": 1.0}, {"source": "concept_offline_first_architecture", "target": "concept_idempotent_sync", "relation": "conceptually_related_to", "confidence": "EXTRACTED", "confidence_score": 1.0, "source_file": "AGENTS.md", "source_location": null, "weight": 1.0}, {"source": "concept_crecer_methodology", "target": "concept_cms_publication_workflow", "relation": "conceptually_related_to", "confidence": "EXTRACTED", "confidence_score": 1.0, "source_file": "AGENTS.md", "source_location": null, "weight": 1.0}, {"source": "concept_crecer_methodology", "target": "concept_content_state_machine", "relation": "conceptually_related_to", "confidence": "EXTRACTED", "confidence_score": 1.0, "source_file": "AGENTS.md", "source_location": null, "weight": 1.0}, {"source": "concept_minor_protection_security", "target": "concept_role_based_access_control", "relation": "conceptually_related_to", "confidence": "EXTRACTED", "confidence_score": 1.0, "source_file": "AGENTS.md", "source_location": null, "weight": 1.0}, {"source": "concept_minor_protection_security", "target": "concept_supabase_rls_second_layer", "relation": "conceptually_related_to", "confidence": "EXTRACTED", "confidence_score": 1.0, "source_file": "AGENTS.md", "source_location": null, "weight": 1.0}, {"source": "concept_pwa_instalable", "target": "concept_offline_first_architecture", "relation": "conceptually_related_to", "confidence": "EXTRACTED", "confidence_score": 1.0, "source_file": "AGENTS.md", "source_location": null, "weight": 1.0}], "hyperedges": [{"id": "crecer_content_system", "label": "CRECER Content System (Methodology + Age Groups + Paths + CMS Workflow)", "nodes": ["concept_crecer_methodology", "concept_franjas_edad", "concept_sendas_trinitarias", "concept_cms_publication_workflow", "concept_content_state_machine"], "relation": "participate_in", "confidence": "EXTRACTED", "confidence_score": 0.95, "source_file": "AGENTS.md"}, {"id": "offline_sync_architecture", "label": "Offline-First Sync Architecture (Offline-First + Dexie Outbox + Idempotent Sync + Signed URLs)", "nodes": ["concept_offline_first_architecture", "concept_dexie_outbox", "concept_idempotent_sync", "concept_signed_urls", "concept_pwa_instalable"], "relation": "form", "confidence": "EXTRACTED", "confidence_score": 0.95, "source_file": "AGENTS.md"}, {"id": "security_model_for_minors", "label": "Minor Protection Security Model (RBAC + RLS + Media Bucket + Content Approval)", "nodes": ["concept_minor_protection_security", "concept_role_based_access_control", "concept_supabase_rls_second_layer", "concept_media_private_bucket", "concept_cms_publication_workflow"], "relation": "implement", "confidence": "EXTRACTED", "confidence_score": 0.95, "source_file": "AGENTS.md"}]}